dbg/__init__.py
dbg/dbg.py
pdbg/__init__.py
pdbg/pdbg.py
dbg_print_tool-1.0.22.dist-info/METADATA
dbg_print_tool-1.0.22.dist-info/WHEEL
dbg_print_tool-1.0.22.dist-info/top_level.txt
dbg_print_tool-1.0.22.dist-info/RECORD
