Metadata-Version: 2.1
Name: dbg-print-tool
Version: 1.0.22
Summary: Herramienta para debugear codigo
Author: ROKO108
Project-URL: Homepage, https://github.com/ROKO108/dbg
Project-URL: Bug Tracker, https://github.com/ROKO108/dbg/issues
Classifier: Programming Language :: Python :: 3
Classifier: License :: OSI Approved :: MIT License
Classifier: Operating System :: OS Independent
Requires-Python: >=3.8
